kateb/__init__.py
kateb/table_manager.py
kateb/web_table.py
kateb-0.0.6.dist-info/METADATA
kateb-0.0.6.dist-info/WHEEL
kateb-0.0.6.dist-info/licenses/LICENSE
kateb-0.0.6.dist-info/RECORD
