Metadata-Version: 2.1
Name: kateb
Version: 0.0.6
Summary: A Simple Tool for Extractind Tables from Webpages
Project-URL: Homepage, https://github.com/m-amin-alavian/kateb
Project-URL: Bug Tracker, https://github.com/m-amin-alavian/kateb/issues
Author-email: mohammad amin alavian <m.amin.alavian@gmail.com>
License: MIT License
Classifier: License :: OSI Approved :: MIT License
Classifier: Operating System :: OS Independent
Classifier: Programming Language :: Python :: 3
Requires-Python: >=3.7
